psankey/__init__.py
psankey/sankey.py
psankey-1.0.1.dist-info/LICENSE
psankey-1.0.1.dist-info/METADATA
psankey-1.0.1.dist-info/WHEEL
psankey-1.0.1.dist-info/top_level.txt
psankey-1.0.1.dist-info/RECORD
