Metadata-Version: 2.1
Name: psankey
Version: 1.0.1
Summary: Package for plotting Sankey diagrams with Python
Home-page: https://github.com/mandalsubhajit/psankey
Author: Subhajit Mandal
Author-email: mandalsubhajit@gmail.com
License: UNKNOWN
Platform: UNKNOWN
Classifier: Programming Language :: Python :: 3
Classifier: License :: OSI Approved :: MIT License
Classifier: Operating System :: OS Independent
Requires-Python: >=3.6
